{"1234206650753585153": {"created_at": "Sun Mar 01 19:59:30 +0000 2020", "user_id": 1187835922118787073, "text": "RT @realDonaldTrump: Thank you to all of the incredible Law Enforcement Officers in South Carolina tonight. We love you! https://t.co/yoqjw\u2026", "is_quoted": false, "quoted_id": null}, "1234206810011316224": {"created_at": "Sun Mar 01 20:00:08 +0000 2020", "user_id": 34713362, "text": "As many as 95% of employers admit to hiring the wrong people each year (via @bopinion) https://t.co/U3u66wtjU2", "is_quoted": false, "quoted_id": null}, "1234206866290462722": {"created_at": "Sun Mar 01 20:00:22 +0000 2020", "user_id": 3108351, "text": "Nine Southern schools are among the top 20 public colleges in the country in the WSJ/THE College Rankings https://t.co/mO73qIOdjb", "is_quoted": false, "quoted_id": null}, "1234207150026547200": {"created_at": "Sun Mar 01 20:01:29 +0000 2020", "user_id": 14276189, "text": "So it begins! (Thanks all for the very kind comments. I\u2019ll keep you updated. Warm-up acts tomorrow and Tuesday. Main  Event Wednesday.) https://t.co/PFR5SGXhlG", "is_quoted": false, "quoted_id": null}, "1234209189649616898": {"created_at": "Sun Mar 01 20:09:35 +0000 2020", "user_id": 1015965765940498434, "text": "Fake news, duder. https://t.co/1fbbrbl2tm", "is_quoted": true, "quoted_id": 1234207690479587331}, "1234209727430656000": {"created_at": "Sun Mar 01 20:11:44 +0000 2020", "user_id": 34713362, "text": "Members of the indigenous group at the center of protests that have threatened Canada\u2019s economy in recent weeks have reached a proposed deal with the government https://t.co/8n4InQojpJ", "is_quoted": false, "quoted_id": null}, "1234210289224056832": {"created_at": "Sun Mar 01 20:13:58 +0000 2020", "user_id": 286654612, "text": "MARKET POLL:\nWas the COVID-19 news over the weekend worse, same, or better than what you expected when US markets closed on Friday?", "is_quoted": false, "quoted_id": null}}