{"1235188582387679233": {"created_at": "Wed Mar 04 13:01:21 +0000 2020", "user_id": 35782209, "text": "@realDonaldTrump Is Bernie your new best friend?", "is_quoted": false, "quoted_id": null}, "1235188887657385984": {"created_at": "Wed Mar 04 13:02:34 +0000 2020", "user_id": 286654612, "text": "Zeno's paradox of (e)motion", "is_quoted": true, "quoted_id": 1235166917326974976}, "1235189091135868928": {"created_at": "Wed Mar 04 13:03:22 +0000 2020", "user_id": 28571999, "text": "Italy closes schools and universities nationwide.", "is_quoted": false, "quoted_id": null}, "1235189281959940097": {"created_at": "Wed Mar 04 13:04:08 +0000 2020", "user_id": 34713362, "text": "Former Rep. Pete Sessions clinches a spot in a GOP primary runoff in a different Texas district than the one he represented in Congress for 22 years https://t.co/PFL1thNr3q", "is_quoted": false, "quoted_id": null}, "1235189496876019712": {"created_at": "Wed Mar 04 13:04:59 +0000 2020", "user_id": 3108351, "text": "U.S. stock futures rise sharply as investors digest #SuperTuesday results and the impact of the Fed\u2019s surprise rate cut https://t.co/WYbyNXY20a", "is_quoted": false, "quoted_id": null}, "1235190850621067264": {"created_at": "Wed Mar 04 13:10:22 +0000 2020", "user_id": 286654612, "text": "You know you may be a Boomer if...\n\nYou claim to be a free market libertarian but also insist the government provide you a safe savings vehicle with a high enough rate of interest for retirement", "is_quoted": false, "quoted_id": null}, "1235191287999090689": {"created_at": "Wed Mar 04 13:12:06 +0000 2020", "user_id": 34713362, "text": "BREAKING: Italy will shut down schools across the country until mid-March to curb the spread of the coronavirus epidemic https://t.co/DEG0oM6avj https://t.co/hISwukCkRg", "is_quoted": false, "quoted_id": null}, "1235192040171896834": {"created_at": "Wed Mar 04 13:15:05 +0000 2020", "user_id": 3108351, "text": "Travelers returning from coronavirus hot spots find little clarity on quarantining https://t.co/8LNB7Zgfxa", "is_quoted": false, "quoted_id": null}, "1235192046740267008": {"created_at": "Wed Mar 04 13:15:07 +0000 2020", "user_id": 34713362, "text": "China is slowly going back to work. Pollution data from space shows uneven economic recovery from virus. https://t.co/17BsczQIrk https://t.co/bSY8GCMgYR", "is_quoted": false, "quoted_id": null}, "1235192234984775686": {"created_at": "Wed Mar 04 13:15:52 +0000 2020", "user_id": 22522178, "text": "Getting a lot of feedback for my rant on yesterday\u2019s rate cut on @HalftimeReport (video here) - most seem to agree with me although many take issue with my hair style. \n\nhttps://t.co/zSYUm1nTNF", "is_quoted": false, "quoted_id": null}}