{"1235332055178899458": {"created_at": "Wed Mar 04 22:31:27 +0000 2020", "user_id": 1233125795889123329, "text": "RT @realDonaldTrump: Pandering Mini Mike Bloomberg, along with his wacky friend, Tom Steyer, have found out the hard way that you can\u2019t buy\u2026", "is_quoted": false, "quoted_id": null}, "1235332123827089409": {"created_at": "Wed Mar 04 22:31:44 +0000 2020", "user_id": 34939208, "text": "is $PLNT the only fitness chain left? Guess $CLUB still trades.", "is_quoted": true, "quoted_id": 1235322089109942273}, "1235332212742148102": {"created_at": "Wed Mar 04 22:32:05 +0000 2020", "user_id": 34713362, "text": "A new thirst-quenching canned spirit finds the middle ground between cocktails and beer https://t.co/WM7wbDfhfM", "is_quoted": false, "quoted_id": null}, "1235332857305927680": {"created_at": "Wed Mar 04 22:34:39 +0000 2020", "user_id": 34713362, "text": "The world\u2019s biggest polluter is setting aside its lofty environmental ambitions as it confronts an unprecedented slowdown in growth https://t.co/8FNIw33MIt", "is_quoted": false, "quoted_id": null}, "1235332973098151940": {"created_at": "Wed Mar 04 22:35:06 +0000 2020", "user_id": 34713362, "text": "Plans for one of the world\u2019s biggest electronic-music events were in up in the air Wednesday as Miami's mayor met with Ultra Music Festival organizers over coronavirus concerns https://t.co/VCnOqnV9d6", "is_quoted": false, "quoted_id": null}, "1235332977598570498": {"created_at": "Wed Mar 04 22:35:07 +0000 2020", "user_id": 34713362, "text": "Democratic primary voters had toyed with a number of possible suitors, but late-deciding voters overwhelmingly turned to former front-runner Joe Biden https://t.co/BNeD3u1mJr", "is_quoted": false, "quoted_id": null}, "1235333897447247874": {"created_at": "Wed Mar 04 22:38:47 +0000 2020", "user_id": 1469603575, "text": "If there\u2019s one area for optimism over coronavirus I\u2019ve deduced over the last few days it\u2019s that often, early in an epidemic, mild cases aren\u2019t usually reported. Which may mean the fatality rate could revert to a lower mean. But, again, all speculation. Lots up in the air.", "is_quoted": false, "quoted_id": null}, "1235334244815310848": {"created_at": "Wed Mar 04 22:40:10 +0000 2020", "user_id": 108021761, "text": "Stocks Get A Boost From Biden Win https://t.co/inHJhZTmE1 @GorillaTrades", "is_quoted": false, "quoted_id": null}, "1235334789168795653": {"created_at": "Wed Mar 04 22:42:19 +0000 2020", "user_id": 702585281, "text": "\u201cAlign Tech to buy dental software maker Exocad\u201d (EUR376 million in cash) $ALGN https://t.co/tWqrmwW1Hk", "is_quoted": false, "quoted_id": null}, "1235335237544087552": {"created_at": "Wed Mar 04 22:44:06 +0000 2020", "user_id": 34713362, "text": "Goldman agreed to change how much it pays some board members to settle a shareholder lawsuit https://t.co/zsZHn0fRhy", "is_quoted": false, "quoted_id": null}, "1235335475038212096": {"created_at": "Wed Mar 04 22:45:03 +0000 2020", "user_id": 3108351, "text": "Search-and-rescue teams in Tennessee continued to look for survivors in hard-hit Putnam County, east of Nashville, a day after tornadoes tore across the state and left a trail of ruin https://t.co/0qSxDXrhMv", "is_quoted": false, "quoted_id": null}, "1235335483393298440": {"created_at": "Wed Mar 04 22:45:05 +0000 2020", "user_id": 34713362, "text": "Roku said it has no plans to create its own shows right now https://t.co/X4LtgigFL7", "is_quoted": false, "quoted_id": null}}