{"1235671906491265041": {"created_at": "Thu Mar 05 21:01:54 +0000 2020", "user_id": 763377478349967361, "text": "@realDonaldTrump @RonaldKlain What the absolute fuck", "is_quoted": false, "quoted_id": null}, "1235671962392752128": {"created_at": "Thu Mar 05 21:02:08 +0000 2020", "user_id": 142742259, "text": "buy supermarkets/warehouse clubs; sell restaurants and stay home and watch Netflix? @HedgeyeComm", "is_quoted": false, "quoted_id": null}, "1235672446063308816": {"created_at": "Thu Mar 05 21:04:03 +0000 2020", "user_id": 34713362, "text": "The International Energy Agency plans to revise down its oil-demand forecasts next week because of the spreading coronavirus. https://t.co/0UHCq6K2WO", "is_quoted": false, "quoted_id": null}, "1235672548651577344": {"created_at": "Thu Mar 05 21:04:27 +0000 2020", "user_id": 1469603575, "text": "NEW PODCAST: Quoth the Raven #178 - Peter Schiff on Coronavirus, Gold, Markets and Recession @peterschiff https://t.co/zALDhvMjAb", "is_quoted": false, "quoted_id": null}, "1235672630822187008": {"created_at": "Thu Mar 05 21:04:47 +0000 2020", "user_id": 34713362, "text": "U.S. coal use plunged more than 13% in 2019, the most in 65 years https://t.co/zNULyL1dJ6", "is_quoted": false, "quoted_id": null}, "1235673229156446209": {"created_at": "Thu Mar 05 21:07:10 +0000 2020", "user_id": 223238349, "text": "Joe Nocerror is the Donald Trump of  @bopinion @opinion_joe .. You have a big problem on your hands with him Tim @mimedx", "is_quoted": true, "quoted_id": 1235639150092705794}, "1235673327819087872": {"created_at": "Thu Mar 05 21:07:33 +0000 2020", "user_id": 142742259, "text": "Yes, even before everyone stays home, sales were collapsing, and the weather was amazing! Same data different spin! Pictures are worth a thousand words! https://t.co/rEI8ho7obB", "is_quoted": true, "quoted_id": 1235672181000073217}, "1235673462603014144": {"created_at": "Thu Mar 05 21:08:05 +0000 2020", "user_id": 34713362, "text": "Should you buy the dip? That\u2019s for you to decide https://t.co/TzZT95bl1R via @BW", "is_quoted": false, "quoted_id": null}, "1235673951336087552": {"created_at": "Thu Mar 05 21:10:02 +0000 2020", "user_id": 34713362, "text": "Larry Kudlow, Trump\u2019s top economic adviser, is a relentless cheerleader. But is he right? https://t.co/7oNKEDvMuX via @BW", "is_quoted": false, "quoted_id": null}, "1235674211991064576": {"created_at": "Thu Mar 05 21:11:04 +0000 2020", "user_id": 34713362, "text": "India's fast-rising fund CEO has her sights on $40 billion https://t.co/j0emk6IZ8k", "is_quoted": false, "quoted_id": null}, "1235674539268456448": {"created_at": "Thu Mar 05 21:12:22 +0000 2020", "user_id": 3195244375, "text": "Obviously we\u2019re gonna be +4% tomorrow, timestamp, send tweet", "is_quoted": false, "quoted_id": null}, "1235674711201202176": {"created_at": "Thu Mar 05 21:13:03 +0000 2020", "user_id": 34713362, "text": "\u201cHe was the most demanding and relentlessly challenging person I have ever met.\u201d Businessweek\u2019s former executive editor John Byrne remembers late GE CEO Jack Welch https://t.co/LkdjpCi1wL via @BW", "is_quoted": false, "quoted_id": null}, "1235675233044107264": {"created_at": "Thu Mar 05 21:15:07 +0000 2020", "user_id": 3108351, "text": "A sharp drop-off in foreign tourists and spending by Italian households since the coronavirus outbreak threatens to have knock-on effects for the rest of the economy\u2014and Europe https://t.co/czjNBAXJfB", "is_quoted": false, "quoted_id": null}}