{"1235702108319408128": {"created_at": "Thu Mar 05 23:01:55 +0000 2020", "user_id": 91935657, "text": "RT @realDonaldTrump: Mini Mike, you\u2019re easy! https://t.co/rxFiqSB9RQ", "is_quoted": true, "quoted_id": 1235232463045177344}, "1235702900074176512": {"created_at": "Thu Mar 05 23:05:04 +0000 2020", "user_id": 34713362, "text": "Toshiba Machine is bracing for \u201ca very tough battle\u201d with controversial activist investor Yoshiaki Murakami https://t.co/nzklClOAz4", "is_quoted": false, "quoted_id": null}, "1235703150461493249": {"created_at": "Thu Mar 05 23:06:03 +0000 2020", "user_id": 34713362, "text": "Costco posted blowout February sales as customers began to stockpile goods in response to the coronavirus outbreak https://t.co/6IFN7XqC56", "is_quoted": false, "quoted_id": null}, "1235703152315334656": {"created_at": "Thu Mar 05 23:06:04 +0000 2020", "user_id": 34713362, "text": "Prime Minister Narendra Modi has launched India\u2019s biggest-ever asset sale, putting some of the nation\u2019s corporate icons on the block https://t.co/iTQxR3Ljqp", "is_quoted": false, "quoted_id": null}, "1235703153540173834": {"created_at": "Thu Mar 05 23:06:04 +0000 2020", "user_id": 142742259, "text": "Starbucks says the China coronavirus outbreak will cost it up to $430M https://t.co/a1VBn8Ikbg", "is_quoted": false, "quoted_id": null}, "1235703906719522816": {"created_at": "Thu Mar 05 23:09:04 +0000 2020", "user_id": 34713362, "text": "An heiress to one of South Korea's biggest conglomerates is helping to engineer a shareholder revolt against her CEO brother https://t.co/CpFf3FqtsX", "is_quoted": false, "quoted_id": null}, "1235703908703629313": {"created_at": "Thu Mar 05 23:09:04 +0000 2020", "user_id": 34713362, "text": "Jana can't just \"take that money and run,\" Dyal says in its lawsuit https://t.co/Fvd4rkV515", "is_quoted": false, "quoted_id": null}, "1235705209952899075": {"created_at": "Thu Mar 05 23:14:15 +0000 2020", "user_id": 28571999, "text": "If it ended today this would be the second best week for the S&amp;P 500 in the last six months.", "is_quoted": false, "quoted_id": null}, "1235705356480741376": {"created_at": "Thu Mar 05 23:14:49 +0000 2020", "user_id": 1289436835, "text": "Has $XOM gone the way of $GE and $IBM before it? Still great reputation but starting to rot on the inside because run by bean counters fighting the last war and anyone entrepreneurial has left?", "is_quoted": false, "quoted_id": null}, "1235705405784772609": {"created_at": "Thu Mar 05 23:15:01 +0000 2020", "user_id": 34713362, "text": "Alberta\u2019s premier is backing Erin O\u2019Toole\u2019s campaign to lead the Conservative Party against Justin Trudeau https://t.co/vZz6lb5Qsu", "is_quoted": false, "quoted_id": null}, "1235705405860229122": {"created_at": "Thu Mar 05 23:15:01 +0000 2020", "user_id": 34713362, "text": "AMD's CEO predicted the company will achieve revenue growth of 20% over \u201cthe long term\u201d and become more profitable as it reaches that goal https://t.co/BhgyIzAwMi", "is_quoted": false, "quoted_id": null}, "1235705421589078016": {"created_at": "Thu Mar 05 23:15:05 +0000 2020", "user_id": 3108351, "text": "Many companies are encouraging employees to work from home\u2014or at least be prepared to do so\u2014because of the spreading coronavirus. Time to update your tech! https://t.co/Giek2OVXwR", "is_quoted": false, "quoted_id": null}, "1235705652346945537": {"created_at": "Thu Mar 05 23:16:00 +0000 2020", "user_id": 560294989, "text": "Cc @matthewstoller", "is_quoted": true, "quoted_id": 1235582400823988225}}