{"1236380366849675264": {"created_at": "Sat Mar 07 19:57:04 +0000 2020", "user_id": 34713362, "text": "Wall Street banks worry that breaking up trading teams to have them work from home will make it a lot more difficult to manage risk https://t.co/MJ0gO4BJD6", "is_quoted": false, "quoted_id": null}, "1236381034222170112": {"created_at": "Sat Mar 07 19:59:44 +0000 2020", "user_id": 34713362, "text": "Elbow-bumping? No, that's also too risky https://t.co/t4fbl9g3gZ", "is_quoted": false, "quoted_id": null}, "1236381103071449088": {"created_at": "Sat Mar 07 20:00:00 +0000 2020", "user_id": 22522178, "text": "Inside the World's Largest Bitcoin Fund \n\nhttps://t.co/vlEgBRlvDX", "is_quoted": false, "quoted_id": null}, "1236381134117888010": {"created_at": "Sat Mar 07 20:00:07 +0000 2020", "user_id": 3108351, "text": "From @WSJopinion: Schumer\u2019s tirade takes bullying the judiciary to a new level, and all those who claim to believe in democratic norms should call him out https://t.co/lxGIG6lsHX", "is_quoted": false, "quoted_id": null}, "1236382455717941249": {"created_at": "Sat Mar 07 20:05:22 +0000 2020", "user_id": 34713362, "text": "Ciara postpones concert because of the coronavirus outbreak https://t.co/HnBBED4AD2", "is_quoted": false, "quoted_id": null}}