{"1236903242237243392": {"created_at": "Mon Mar 09 06:34:48 +0000 2020", "user_id": 20636215, "text": "take it for what it's worth (given the  rare # of cases), but the odds don't seem necessarily stacked in your favor for an immediate 'V' shaped reversion in oil price, after these kinds of moves. Again, low N, so i would place no confidence either way.", "is_quoted": false, "quoted_id": null}, "1236904695907545088": {"created_at": "Mon Mar 09 06:40:34 +0000 2020", "user_id": 20636215, "text": "Last week (thursday/friday), I saw someone say $8 oil for WTI... I thought that was crazy. lol", "is_quoted": false, "quoted_id": null}, "1236906089628807168": {"created_at": "Mon Mar 09 06:46:07 +0000 2020", "user_id": 34713362, "text": "Even virtual goods from China are taking a hit from the coronavirus https://t.co/APzdMBGqft", "is_quoted": false, "quoted_id": null}, "1236906337306624000": {"created_at": "Mon Mar 09 06:47:06 +0000 2020", "user_id": 34713362, "text": "Should you wear a mask? Here's what the experts say https://t.co/jS8E2GFC4k", "is_quoted": false, "quoted_id": null}, "1236906433469243392": {"created_at": "Mon Mar 09 06:47:29 +0000 2020", "user_id": 20636215, "text": "Trump tomorrow: \"I WORKED WITH THE SAUDIS TO BRING LOWER PRICES FOR AMERICANS DURING THIS CORONA CRISIS. TAX CUT! #MAKEAMERICAGREATAGAIN \"", "is_quoted": false, "quoted_id": null}}