{"1236978805761335297": {"created_at": "Mon Mar 09 11:35:03 +0000 2020", "user_id": 34713362, "text": "The coronavirus causes little more than a cough if it stays in the nose and throat. Danger starts when it reaches the lung https://t.co/hytt2fSUMi", "is_quoted": false, "quoted_id": null}, "1236979155704492032": {"created_at": "Mon Mar 09 11:36:27 +0000 2020", "user_id": 20636215, "text": "Today is the day to be a hero", "is_quoted": false, "quoted_id": null}, "1236979322071678977": {"created_at": "Mon Mar 09 11:37:07 +0000 2020", "user_id": 34713362, "text": "Tellurian lays off 40% of staff to slash costs and rescue a struggling $29 billion LNG project https://t.co/E0x0C9qBEc", "is_quoted": false, "quoted_id": null}, "1236979946175725568": {"created_at": "Mon Mar 09 11:39:35 +0000 2020", "user_id": 25073877, "text": "\u201cTrump has outmastered the Deep State. He\u2019s light years ahead of us.\u201d MSDNC. I disagree. We have a long way to go. There are still some very bad, sick people in our government - people who do not love our Country (In fact, they hate our Country!).", "is_quoted": false, "quoted_id": null}, "1236980284744241154": {"created_at": "Mon Mar 09 11:40:56 +0000 2020", "user_id": 25073877, "text": "The Obama/Biden Administration is the most corrupt Administration in the history of our Country!", "is_quoted": false, "quoted_id": null}, "1236980579419271170": {"created_at": "Mon Mar 09 11:42:06 +0000 2020", "user_id": 34713362, "text": "Boris Johnson's first Budget is looking cursed https://t.co/NQkJ1uODwY", "is_quoted": false, "quoted_id": null}, "1236980820797243393": {"created_at": "Mon Mar 09 11:43:04 +0000 2020", "user_id": 1469603575, "text": "30x more severe", "is_quoted": true, "quoted_id": 1236980576831377409}, "1236981328576380929": {"created_at": "Mon Mar 09 11:45:05 +0000 2020", "user_id": 3108351, "text": "\"These are episodes of looting\u2026at a time when these health devices are so important,\" said the director of a hospital in virus-stricken Italy https://t.co/mJEqSLiie3", "is_quoted": false, "quoted_id": null}, "1236981335371264000": {"created_at": "Mon Mar 09 11:45:07 +0000 2020", "user_id": 34713362, "text": "Poland\u2019s dispute with Europe over the country\u2019s political purge of judges has turned into a game of chicken https://t.co/iO4REHrDsS", "is_quoted": false, "quoted_id": null}, "1236982073832996864": {"created_at": "Mon Mar 09 11:48:03 +0000 2020", "user_id": 34713362, "text": "Pressure is growing on Trump to take more decisive action in response to the virus outbreak, as the number of cases in the U.S. and worldwide continues to grow https://t.co/L66VIp3Q3M", "is_quoted": false, "quoted_id": null}, "1236982073962967041": {"created_at": "Mon Mar 09 11:48:03 +0000 2020", "user_id": 34713362, "text": "Are you helping spread coronavirus contagion on your Twitter and Facebook feeds? https://t.co/k8eohsk2Hc via @bopinion", "is_quoted": false, "quoted_id": null}}