{"1237738818649894912": {"created_at": "Wed Mar 11 13:55:05 +0000 2020", "user_id": 34713362, "text": "Iran urges the U.S. to ease sanctions on imports of medicines and foods needed to fight a major outbreak of the coronavirus https://t.co/jUWdruiXCL", "is_quoted": false, "quoted_id": null}, "1237738973562273793": {"created_at": "Wed Mar 11 13:55:42 +0000 2020", "user_id": 1961333743, "text": "Age cohort with low voter turnout blames things they don\u2019t like for not voting. Got it. #OkBoomer", "is_quoted": true, "quoted_id": 1237547634111348736}, "1237739327263817729": {"created_at": "Wed Mar 11 13:57:06 +0000 2020", "user_id": 3108351, "text": "The number of U.S. cases reached 1,025 Tuesday night https://t.co/R1zNNFtUU4", "is_quoted": false, "quoted_id": null}, "1237739539810209793": {"created_at": "Wed Mar 11 13:57:57 +0000 2020", "user_id": 35499699, "text": "$TRUP out with a presser to remind everyone that this loss making insurance company continues to try to rub that Berkshire Hathaway \"shine\" on the biz by hosting a \"Founder led Q&amp;A\" around the annual Buffett gathering.  One of many absurd IR tools this co. has used over the yrs", "is_quoted": false, "quoted_id": null}, "1237740143500394496": {"created_at": "Wed Mar 11 14:00:20 +0000 2020", "user_id": 319102548, "text": "Someone please let me know when Warren or Jerome are drawing a nice Mr. Bubbles bubble bath.  \n\nTIA!\n\nhttps://t.co/gudnSey37x", "is_quoted": false, "quoted_id": null}, "1237740322890944512": {"created_at": "Wed Mar 11 14:01:03 +0000 2020", "user_id": 34713362, "text": "Harvey Weinstein will be sentenced Wednesday for sexual assault https://t.co/Sh83PvP2TJ", "is_quoted": false, "quoted_id": null}, "1237740704614367237": {"created_at": "Wed Mar 11 14:02:34 +0000 2020", "user_id": 286654612, "text": "Definite squeeze going on in $NG_F", "is_quoted": false, "quoted_id": null}, "1237740858218295297": {"created_at": "Wed Mar 11 14:03:11 +0000 2020", "user_id": 2188619364, "text": "Betcha a signed dollar that Tesla's Fremont plant will/would be the last manufacturing plant of any kind in the U.S. to close, and only then because parts would have run out.  #OtherColds https://t.co/qjwci1DD8C", "is_quoted": false, "quoted_id": null}, "1237741546751045637": {"created_at": "Wed Mar 11 14:05:55 +0000 2020", "user_id": 2188619364, "text": "Cineworld bank loans getting carpet bombed now.  Thoughts and prayers to the $CGX.TO shareholders hoping their $34 buyout closes.  @HindenburgRes https://t.co/umaBdSlMOn", "is_quoted": false, "quoted_id": null}, "1237741880026284032": {"created_at": "Wed Mar 11 14:07:14 +0000 2020", "user_id": 2188619364, "text": "Send these shitcos to the bottom of the ocean.  @VP", "is_quoted": true, "quoted_id": 1237733101213605888}, "1237742116564013056": {"created_at": "Wed Mar 11 14:08:11 +0000 2020", "user_id": 25073877, "text": "Thank you Gavin. Team is doing a great job!", "is_quoted": true, "quoted_id": 1237523131041861632}}